{
  "detection_per_layer": [
    0.5,
    1.0,
    1.0,
    1.0,
    1.0,
    1.0,
    1.0,
    1.0,
    1.0,
    1.0,
    1.0,
    1.0,
    1.0,
    1.0,
    1.0,
    1.0,
    1.0,
    1.0,
    1.0,
    1.0,
    1.0,
    1.0,
    1.0,
    1.0,
    1.0,
    1.0,
    1.0,
    1.0,
    1.0,
    1.0,
    1.0,
    1.0,
    1.0,
    1.0,
    1.0,
    1.0,
    1.0,
    1.0,
    1.0,
    1.0,
    1.0,
    1.0,
    1.0,
    1.0,
    1.0,
    1.0,
    1.0,
    1.0,
    1.0
  ],
  "detection_peak_layer": 1,
  "detection_peak_acc": 1.0,
  "axis_decoding": {
    "classes": [
      "entity_scope",
      "metric_definition"
    ],
    "n": 157,
    "baseline": 0.599,
    "per_layer_acc": [
      0.599,
      0.599,
      0.599,
      0.592,
      0.631,
      0.72,
      0.758,
      0.771,
      0.777,
      0.784,
      0.784,
      0.784,
      0.783,
      0.783,
      0.79,
      0.796,
      0.796,
      0.796,
      0.796,
      0.796,
      0.796,
      0.796,
      0.796,
      0.796,
      0.796,
      0.796,
      0.79,
      0.777,
      0.757,
      0.757,
      0.757,
      0.751,
      0.751,
      0.751,
      0.751,
      0.751,
      0.751,
      0.751,
      0.745,
      0.745,
      0.732,
      0.745,
      0.732,
      0.726,
      0.714,
      0.7,
      0.714,
      0.707,
      0.694
    ]
  }
}